gitfix/__init__.py
gitfix/git_states.py
gitfix/main.py
gitfix/state.py
gitfix-0.2.3.dist-info/entry_points.txt
gitfix-0.2.3.dist-info/LICENSE.md
gitfix-0.2.3.dist-info/WHEEL
gitfix-0.2.3.dist-info/METADATA
gitfix-0.2.3.dist-info/RECORD
